{"candidates": [{"party": "Democratic", "votes": {"popular": {"percentage": 0.5008, "count": 40831881}}, "name": "Jimmy Carter"}, {"party": "Republican", "votes": {"popular": {"percentage": 0.4802, "count": 39148634}}, "name": "Gerald Ford"}, {"party": "Independent", "votes": {"popular": {"percentage": 0.0091, "count": 740460}}, "name": "Eugene McCarthy"}, {"party": "Libertarian", "votes": {"popular": {"percentage": 0.0021, "count": 172557}}, "name": "Roger MacBride"}], "stateResults": [{"candidateData": {"Eugene McCarthy": {"popularVoteTotal": 0, "popularVotePercentage": "0.0000"}, "Jimmy Carter": {"popularVoteTotal": 659170, "popularVotePercentage": "0.5573"}, "Roger MacBride": {"popularVoteTotal": 1481, "popularVotePercentage": "0.0013"}, "Gerald Ford": {"popularVoteTotal": 504070, "popularVotePercentage": "0.4261"}}, "topCandidate": "Jimmy Carter", "electoralVotes": "9", "name": "Alabama"}, {"candidateData": {"Eugene McCarthy": {"popularVoteTotal": 0, "popularVotePercentage": "0.0000"}, "Jimmy Carter": {"popularVoteTotal": 44058, "popularVotePercentage": "0.3565"}, "Roger MacBride": {"popularVoteTotal": 6785, "popularVotePercentage": "0.0549"}, "Gerald Ford": {"popularVoteTotal": 71555, "popularVotePercentage": "0.5790"}}, "topCandidate": "Gerald Ford", "electoralVotes": "3", "name": "Alaska"}, {"candidateData": {"Eugene McCarthy": {"popularVoteTotal": 19229, "popularVotePercentage": "0.0259"}, "Jimmy Carter": {"popularVoteTotal": 295602, "popularVotePercentage": "0.3980"}, "Roger MacBride": {"popularVoteTotal": 7647, "popularVotePercentage": "0.0103"}, "Gerald Ford": {"popularVoteTotal": 418642, "popularVotePercentage": "0.5637"}}, "topCandidate": "Gerald Ford", "electoralVotes": "6", "name": "Arizona"}, {"candidateData": {"Eugene McCarthy": {"popularVoteTotal": 647, "popularVotePercentage": "0.0008"}, "Jimmy Carter": {"popularVoteTotal": 499614, "popularVotePercentage": "0.6494"}, "Roger MacBride": {"popularVoteTotal": 0, "popularVotePercentage": "0.0000"}, "Gerald Ford": {"popularVoteTotal": 268753, "popularVotePercentage": "0.3493"}}, "topCandidate": "Jimmy Carter", "electoralVotes": "6", "name": "Arkansas"}, {"candidateData": {"Eugene McCarthy": {"popularVoteTotal": 58412, "popularVotePercentage": "0.0074"}, "Jimmy Carter": {"popularVoteTotal": 3742284, "popularVotePercentage": "0.4757"}, "Roger MacBride": {"popularVoteTotal": 56388, "popularVotePercentage": "0.0072"}, "Gerald Ford": {"popularVoteTotal": 3882244, "popularVotePercentage": "0.4935"}}, "topCandidate": "Gerald Ford", "electoralVotes": "45", "name": "California"}, {"candidateData": {"Eugene McCarthy": {"popularVoteTotal": 26107, "popularVotePercentage": "0.0241"}, "Jimmy Carter": {"popularVoteTotal": 460353, "popularVotePercentage": "0.4258"}, "Roger MacBride": {"popularVoteTotal": 5330, "popularVotePercentage": "0.0049"}, "Gerald Ford": {"popularVoteTotal": 584367, "popularVotePercentage": "0.5405"}}, "topCandidate": "Gerald Ford", "electoralVotes": "7", "name": "Colorado"}, {"candidateData": {"Eugene McCarthy": {"popularVoteTotal": 0, "popularVotePercentage": "0.0000"}, "Jimmy Carter": {"popularVoteTotal": 647895, "popularVotePercentage": "0.4690"}, "Roger MacBride": {"popularVoteTotal": 0, "popularVotePercentage": "0.0000"}, "Gerald Ford": {"popularVoteTotal": 719261, "popularVotePercentage": "0.5206"}}, "topCandidate": "Gerald Ford", "electoralVotes": "8", "name": "Connecticut"}, {"candidateData": {"Eugene McCarthy": {"popularVoteTotal": 2437, "popularVotePercentage": "0.0103"}, "Jimmy Carter": {"popularVoteTotal": 122596, "popularVotePercentage": "0.5198"}, "Roger MacBride": {"popularVoteTotal": 0, "popularVotePercentage": "0.0000"}, "Gerald Ford": {"popularVoteTotal": 109831, "popularVotePercentage": "0.4657"}}, "topCandidate": "Jimmy Carter", "electoralVotes": "3", "name": "Delaware"}, {"candidateData": {"Eugene McCarthy": {"popularVoteTotal": 0, "popularVotePercentage": "0.0000"}, "Jimmy Carter": {"popularVoteTotal": 137818, "popularVotePercentage": "0.8163"}, "Roger MacBride": {"popularVoteTotal": 274, "popularVotePercentage": "0.0016"}, "Gerald Ford": {"popularVoteTotal": 27873, "popularVotePercentage": "0.1651"}}, "topCandidate": "Jimmy Carter", "electoralVotes": "3", "name": "D.C."}, {"candidateData": {"Eugene McCarthy": {"popularVoteTotal": 23643, "popularVotePercentage": "0.0075"}, "Jimmy Carter": {"popularVoteTotal": 1636000, "popularVotePercentage": "0.5193"}, "Roger MacBride": {"popularVoteTotal": 103, "popularVotePercentage": "0.0000"}, "Gerald Ford": {"popularVoteTotal": 1469531, "popularVotePercentage": "0.4664"}}, "topCandidate": "Jimmy Carter", "electoralVotes": "17", "name": "Florida"}, {"candidateData": {"Eugene McCarthy": {"popularVoteTotal": 991, "popularVotePercentage": "0.0007"}, "Jimmy Carter": {"popularVoteTotal": 979409, "popularVotePercentage": "0.6674"}, "Roger MacBride": {"popularVoteTotal": 175, "popularVotePercentage": "0.0001"}, "Gerald Ford": {"popularVoteTotal": 483743, "popularVotePercentage": "0.3296"}}, "topCandidate": "Jimmy Carter", "electoralVotes": "12", "name": "Georgia"}, {"candidateData": {"Eugene McCarthy": {"popularVoteTotal": 0, "popularVotePercentage": "0.0000"}, "Jimmy Carter": {"popularVoteTotal": 147375, "popularVotePercentage": "0.5059"}, "Roger MacBride": {"popularVoteTotal": 3923, "popularVotePercentage": "0.0135"}, "Gerald Ford": {"popularVoteTotal": 140003, "popularVotePercentage": "0.4806"}}, "topCandidate": "Jimmy Carter", "electoralVotes": "4", "name": "Hawaii"}, {"candidateData": {"Eugene McCarthy": {"popularVoteTotal": 0, "popularVotePercentage": "0.0000"}, "Jimmy Carter": {"popularVoteTotal": 126549, "popularVotePercentage": "0.3712"}, "Roger MacBride": {"popularVoteTotal": 3558, "popularVotePercentage": "0.0104"}, "Gerald Ford": {"popularVoteTotal": 204151, "popularVotePercentage": "0.5988"}}, "topCandidate": "Gerald Ford", "electoralVotes": "4", "name": "Idaho"}, {"candidateData": {"Eugene McCarthy": {"popularVoteTotal": 55939, "popularVotePercentage": "0.0119"}, "Jimmy Carter": {"popularVoteTotal": 2271295, "popularVotePercentage": "0.4813"}, "Roger MacBride": {"popularVoteTotal": 8057, "popularVotePercentage": "0.0017"}, "Gerald Ford": {"popularVoteTotal": 2364269, "popularVotePercentage": "0.5010"}}, "topCandidate": "Gerald Ford", "electoralVotes": "26", "name": "Illinois"}, {"candidateData": {"Eugene McCarthy": {"popularVoteTotal": 0, "popularVotePercentage": "0.0000"}, "Jimmy Carter": {"popularVoteTotal": 1014714, "popularVotePercentage": "0.4570"}, "Roger MacBride": {"popularVoteTotal": 0, "popularVotePercentage": "0.0000"}, "Gerald Ford": {"popularVoteTotal": 1183958, "popularVotePercentage": "0.5332"}}, "topCandidate": "Gerald Ford", "electoralVotes": "13", "name": "Indiana"}, {"candidateData": {"Eugene McCarthy": {"popularVoteTotal": 20051, "popularVotePercentage": "0.0157"}, "Jimmy Carter": {"popularVoteTotal": 619931, "popularVotePercentage": "0.4846"}, "Roger MacBride": {"popularVoteTotal": 1452, "popularVotePercentage": "0.0011"}, "Gerald Ford": {"popularVoteTotal": 632863, "popularVotePercentage": "0.4947"}}, "topCandidate": "Gerald Ford", "electoralVotes": "8", "name": "Iowa"}, {"candidateData": {"Eugene McCarthy": {"popularVoteTotal": 13185, "popularVotePercentage": "0.0138"}, "Jimmy Carter": {"popularVoteTotal": 430421, "popularVotePercentage": "0.4494"}, "Roger MacBride": {"popularVoteTotal": 3242, "popularVotePercentage": "0.0034"}, "Gerald Ford": {"popularVoteTotal": 502752, "popularVotePercentage": "0.5249"}}, "topCandidate": "Gerald Ford", "electoralVotes": "7", "name": "Kansas"}, {"candidateData": {"Eugene McCarthy": {"popularVoteTotal": 6837, "popularVotePercentage": "0.0059"}, "Jimmy Carter": {"popularVoteTotal": 615717, "popularVotePercentage": "0.5275"}, "Roger MacBride": {"popularVoteTotal": 814, "popularVotePercentage": "0.0007"}, "Gerald Ford": {"popularVoteTotal": 531852, "popularVotePercentage": "0.4557"}}, "topCandidate": "Jimmy Carter", "electoralVotes": "9", "name": "Kentucky"}, {"candidateData": {"Eugene McCarthy": {"popularVoteTotal": 6588, "popularVotePercentage": "0.0052"}, "Jimmy Carter": {"popularVoteTotal": 661365, "popularVotePercentage": "0.5173"}, "Roger MacBride": {"popularVoteTotal": 3325, "popularVotePercentage": "0.0026"}, "Gerald Ford": {"popularVoteTotal": 587446, "popularVotePercentage": "0.4595"}}, "topCandidate": "Jimmy Carter", "electoralVotes": "10", "name": "Louisiana"}, {"candidateData": {"Eugene McCarthy": {"popularVoteTotal": 10874, "popularVotePercentage": "0.0225"}, "Jimmy Carter": {"popularVoteTotal": 232279, "popularVotePercentage": "0.4807"}, "Roger MacBride": {"popularVoteTotal": 10, "popularVotePercentage": "0.0000"}, "Gerald Ford": {"popularVoteTotal": 236320, "popularVotePercentage": "0.4891"}}, "topCandidate": "Gerald Ford", "electoralVotes": "4", "name": "Maine"}, {"candidateData": {"Eugene McCarthy": {"popularVoteTotal": 0, "popularVotePercentage": "0.0000"}, "Jimmy Carter": {"popularVoteTotal": 759612, "popularVotePercentage": "0.5304"}, "Roger MacBride": {"popularVoteTotal": 0, "popularVotePercentage": "0.0000"}, "Gerald Ford": {"popularVoteTotal": 672661, "popularVotePercentage": "0.4696"}}, "topCandidate": "Jimmy Carter", "electoralVotes": "10", "name": "Maryland"}, {"candidateData": {"Eugene McCarthy": {"popularVoteTotal": 65637, "popularVotePercentage": "0.0258"}, "Jimmy Carter": {"popularVoteTotal": 1429475, "popularVotePercentage": "0.5611"}, "Roger MacBride": {"popularVoteTotal": 135, "popularVotePercentage": "0.0001"}, "Gerald Ford": {"popularVoteTotal": 1030276, "popularVotePercentage": "0.4044"}}, "topCandidate": "Jimmy Carter", "electoralVotes": "14", "name": "Massachusetts"}, {"candidateData": {"Eugene McCarthy": {"popularVoteTotal": 47905, "popularVotePercentage": "0.0131"}, "Jimmy Carter": {"popularVoteTotal": 1696714, "popularVotePercentage": "0.4644"}, "Roger MacBride": {"popularVoteTotal": 5406, "popularVotePercentage": "0.0015"}, "Gerald Ford": {"popularVoteTotal": 1893742, "popularVotePercentage": "0.5183"}}, "topCandidate": "Gerald Ford", "electoralVotes": "21", "name": "Michigan"}, {"candidateData": {"Eugene McCarthy": {"popularVoteTotal": 35490, "popularVotePercentage": "0.0182"}, "Jimmy Carter": {"popularVoteTotal": 1070440, "popularVotePercentage": "0.5490"}, "Roger MacBride": {"popularVoteTotal": 3529, "popularVotePercentage": "0.0018"}, "Gerald Ford": {"popularVoteTotal": 819395, "popularVotePercentage": "0.4202"}}, "topCandidate": "Jimmy Carter", "electoralVotes": "10", "name": "Minnesota"}, {"candidateData": {"Eugene McCarthy": {"popularVoteTotal": 4074, "popularVotePercentage": "0.0053"}, "Jimmy Carter": {"popularVoteTotal": 381309, "popularVotePercentage": "0.4956"}, "Roger MacBride": {"popularVoteTotal": 2787, "popularVotePercentage": "0.0036"}, "Gerald Ford": {"popularVoteTotal": 366846, "popularVotePercentage": "0.4768"}}, "topCandidate": "Jimmy Carter", "electoralVotes": "7", "name": "Mississippi"}, {"candidateData": {"Eugene McCarthy": {"popularVoteTotal": 24029, "popularVotePercentage": "0.0123"}, "Jimmy Carter": {"popularVoteTotal": 998387, "popularVotePercentage": "0.5110"}, "Roger MacBride": {"popularVoteTotal": 0, "popularVotePercentage": "0.0000"}, "Gerald Ford": {"popularVoteTotal": 927443, "popularVotePercentage": "0.4747"}}, "topCandidate": "Jimmy Carter", "electoralVotes": "12", "name": "Missouri"}, {"candidateData": {"Eugene McCarthy": {"popularVoteTotal": 0, "popularVotePercentage": "0.0000"}, "Jimmy Carter": {"popularVoteTotal": 149259, "popularVotePercentage": "0.4540"}, "Roger MacBride": {"popularVoteTotal": 0, "popularVotePercentage": "0.0000"}, "Gerald Ford": {"popularVoteTotal": 173703, "popularVotePercentage": "0.5284"}}, "topCandidate": "Gerald Ford", "electoralVotes": "4", "name": "Montana"}, {"candidateData": {"Eugene McCarthy": {"popularVoteTotal": 9409, "popularVotePercentage": "0.0155"}, "Jimmy Carter": {"popularVoteTotal": 233692, "popularVotePercentage": "0.3846"}, "Roger MacBride": {"popularVoteTotal": 1482, "popularVotePercentage": "0.0024"}, "Gerald Ford": {"popularVoteTotal": 359705, "popularVotePercentage": "0.5919"}}, "topCandidate": "Gerald Ford", "electoralVotes": "5", "name": "Nebraska"}, {"candidateData": {"Eugene McCarthy": {"popularVoteTotal": 0, "popularVotePercentage": "0.0000"}, "Jimmy Carter": {"popularVoteTotal": 92479, "popularVotePercentage": "0.4581"}, "Roger MacBride": {"popularVoteTotal": 1519, "popularVotePercentage": "0.0075"}, "Gerald Ford": {"popularVoteTotal": 101273, "popularVotePercentage": "0.5017"}}, "topCandidate": "Gerald Ford", "electoralVotes": "3", "name": "Nevada"}, {"candidateData": {"Eugene McCarthy": {"popularVoteTotal": 4095, "popularVotePercentage": "0.0121"}, "Jimmy Carter": {"popularVoteTotal": 147635, "popularVotePercentage": "0.4347"}, "Roger MacBride": {"popularVoteTotal": 936, "popularVotePercentage": "0.0028"}, "Gerald Ford": {"popularVoteTotal": 185935, "popularVotePercentage": "0.5475"}}, "topCandidate": "Gerald Ford", "electoralVotes": "4", "name": "New Hampshire"}, {"candidateData": {"Eugene McCarthy": {"popularVoteTotal": 32717, "popularVotePercentage": "0.0109"}, "Jimmy Carter": {"popularVoteTotal": 1444653, "popularVotePercentage": "0.4792"}, "Roger MacBride": {"popularVoteTotal": 9449, "popularVotePercentage": "0.0031"}, "Gerald Ford": {"popularVoteTotal": 1509688, "popularVotePercentage": "0.5008"}}, "topCandidate": "Gerald Ford", "electoralVotes": "17", "name": "New Jersey"}, {"candidateData": {"Eugene McCarthy": {"popularVoteTotal": 0, "popularVotePercentage": "0.0000"}, "Jimmy Carter": {"popularVoteTotal": 201148, "popularVotePercentage": "0.4828"}, "Roger MacBride": {"popularVoteTotal": 1110, "popularVotePercentage": "0.0027"}, "Gerald Ford": {"popularVoteTotal": 211419, "popularVotePercentage": "0.5075"}}, "topCandidate": "Gerald Ford", "electoralVotes": "4", "name": "New Mexico"}, {"candidateData": {"Eugene McCarthy": {"popularVoteTotal": 0, "popularVotePercentage": "0.0000"}, "Jimmy Carter": {"popularVoteTotal": 3389558, "popularVotePercentage": "0.5195"}, "Roger MacBride": {"popularVoteTotal": 12197, "popularVotePercentage": "0.0019"}, "Gerald Ford": {"popularVoteTotal": 3100791, "popularVotePercentage": "0.4752"}}, "topCandidate": "Jimmy Carter", "electoralVotes": "41", "name": "New York"}, {"candidateData": {"Eugene McCarthy": {"popularVoteTotal": 0, "popularVotePercentage": "0.0000"}, "Jimmy Carter": {"popularVoteTotal": 927365, "popularVotePercentage": "0.5527"}, "Roger MacBride": {"popularVoteTotal": 2219, "popularVotePercentage": "0.0013"}, "Gerald Ford": {"popularVoteTotal": 741960, "popularVotePercentage": "0.4422"}}, "topCandidate": "Jimmy Carter", "electoralVotes": "13", "name": "North Carolina"}, {"candidateData": {"Eugene McCarthy": {"popularVoteTotal": 2952, "popularVotePercentage": "0.0099"}, "Jimmy Carter": {"popularVoteTotal": 136078, "popularVotePercentage": "0.4580"}, "Roger MacBride": {"popularVoteTotal": 256, "popularVotePercentage": "0.0009"}, "Gerald Ford": {"popularVoteTotal": 153470, "popularVotePercentage": "0.5166"}}, "topCandidate": "Gerald Ford", "electoralVotes": "3", "name": "North Dakota"}, {"candidateData": {"Eugene McCarthy": {"popularVoteTotal": 58258, "popularVotePercentage": "0.0142"}, "Jimmy Carter": {"popularVoteTotal": 2011621, "popularVotePercentage": "0.4892"}, "Roger MacBride": {"popularVoteTotal": 8961, "popularVotePercentage": "0.0022"}, "Gerald Ford": {"popularVoteTotal": 2000505, "popularVotePercentage": "0.4865"}}, "topCandidate": "Jimmy Carter", "electoralVotes": "25", "name": "Ohio"}, {"candidateData": {"Eugene McCarthy": {"popularVoteTotal": 14101, "popularVotePercentage": "0.0129"}, "Jimmy Carter": {"popularVoteTotal": 532442, "popularVotePercentage": "0.4875"}, "Roger MacBride": {"popularVoteTotal": 0, "popularVotePercentage": "0.0000"}, "Gerald Ford": {"popularVoteTotal": 545708, "popularVotePercentage": "0.4996"}}, "topCandidate": "Gerald Ford", "electoralVotes": "8", "name": "Oklahoma"}, {"candidateData": {"Eugene McCarthy": {"popularVoteTotal": 40207, "popularVotePercentage": "0.0390"}, "Jimmy Carter": {"popularVoteTotal": 490407, "popularVotePercentage": "0.4762"}, "Roger MacBride": {"popularVoteTotal": 0, "popularVotePercentage": "0.0000"}, "Gerald Ford": {"popularVoteTotal": 492120, "popularVotePercentage": "0.4778"}}, "topCandidate": "Gerald Ford", "electoralVotes": "6", "name": "Oregon"}, {"candidateData": {"Eugene McCarthy": {"popularVoteTotal": 50584, "popularVotePercentage": "0.0109"}, "Jimmy Carter": {"popularVoteTotal": 2328677, "popularVotePercentage": "0.5040"}, "Roger MacBride": {"popularVoteTotal": 0, "popularVotePercentage": "0.0000"}, "Gerald Ford": {"popularVoteTotal": 2205604, "popularVotePercentage": "0.4773"}}, "topCandidate": "Jimmy Carter", "electoralVotes": "27", "name": "Pennsylvania"}, {"candidateData": {"Eugene McCarthy": {"popularVoteTotal": 479, "popularVotePercentage": "0.0012"}, "Jimmy Carter": {"popularVoteTotal": 227636, "popularVotePercentage": "0.5536"}, "Roger MacBride": {"popularVoteTotal": 715, "popularVotePercentage": "0.0017"}, "Gerald Ford": {"popularVoteTotal": 181249, "popularVotePercentage": "0.4408"}}, "topCandidate": "Jimmy Carter", "electoralVotes": "4", "name": "Rhode Island"}, {"candidateData": {"Eugene McCarthy": {"popularVoteTotal": 0, "popularVotePercentage": "0.0000"}, "Jimmy Carter": {"popularVoteTotal": 450825, "popularVotePercentage": "0.5617"}, "Roger MacBride": {"popularVoteTotal": 0, "popularVotePercentage": "0.0000"}, "Gerald Ford": {"popularVoteTotal": 346140, "popularVotePercentage": "0.4313"}}, "topCandidate": "Jimmy Carter", "electoralVotes": "8", "name": "South Carolina"}, {"candidateData": {"Eugene McCarthy": {"popularVoteTotal": 0, "popularVotePercentage": "0.0000"}, "Jimmy Carter": {"popularVoteTotal": 147068, "popularVotePercentage": "0.4891"}, "Roger MacBride": {"popularVoteTotal": 1619, "popularVotePercentage": "0.0054"}, "Gerald Ford": {"popularVoteTotal": 151505, "popularVotePercentage": "0.5039"}}, "topCandidate": "Gerald Ford", "electoralVotes": "4", "name": "South Dakota"}, {"candidateData": {"Eugene McCarthy": {"popularVoteTotal": 5004, "popularVotePercentage": "0.0034"}, "Jimmy Carter": {"popularVoteTotal": 825879, "popularVotePercentage": "0.5594"}, "Roger MacBride": {"popularVoteTotal": 1375, "popularVotePercentage": "0.0009"}, "Gerald Ford": {"popularVoteTotal": 633969, "popularVotePercentage": "0.4294"}}, "topCandidate": "Jimmy Carter", "electoralVotes": "10", "name": "Tennessee"}, {"candidateData": {"Eugene McCarthy": {"popularVoteTotal": 20118, "popularVotePercentage": "0.0049"}, "Jimmy Carter": {"popularVoteTotal": 2082319, "popularVotePercentage": "0.5114"}, "Roger MacBride": {"popularVoteTotal": 263, "popularVotePercentage": "0.0001"}, "Gerald Ford": {"popularVoteTotal": 1953300, "popularVotePercentage": "0.4797"}}, "topCandidate": "Jimmy Carter", "electoralVotes": "26", "name": "Texas"}, {"candidateData": {"Eugene McCarthy": {"popularVoteTotal": 3907, "popularVotePercentage": "0.0072"}, "Jimmy Carter": {"popularVoteTotal": 182110, "popularVotePercentage": "0.3365"}, "Roger MacBride": {"popularVoteTotal": 2438, "popularVotePercentage": "0.0045"}, "Gerald Ford": {"popularVoteTotal": 337908, "popularVotePercentage": "0.6244"}}, "topCandidate": "Gerald Ford", "electoralVotes": "4", "name": "Utah"}, {"candidateData": {"Eugene McCarthy": {"popularVoteTotal": 4001, "popularVotePercentage": "0.0213"}, "Jimmy Carter": {"popularVoteTotal": 81044, "popularVotePercentage": "0.4314"}, "Roger MacBride": {"popularVoteTotal": 4, "popularVotePercentage": "0.0000"}, "Gerald Ford": {"popularVoteTotal": 102085, "popularVotePercentage": "0.5434"}}, "topCandidate": "Gerald Ford", "electoralVotes": "3", "name": "Vermont"}, {"candidateData": {"Eugene McCarthy": {"popularVoteTotal": 0, "popularVotePercentage": "0.0000"}, "Jimmy Carter": {"popularVoteTotal": 813896, "popularVotePercentage": "0.4796"}, "Roger MacBride": {"popularVoteTotal": 4648, "popularVotePercentage": "0.0027"}, "Gerald Ford": {"popularVoteTotal": 836554, "popularVotePercentage": "0.4929"}}, "topCandidate": "Gerald Ford", "electoralVotes": "12", "name": "Virginia"}, {"candidateData": {"Eugene McCarthy": {"popularVoteTotal": 36986, "popularVotePercentage": "0.0238"}, "Jimmy Carter": {"popularVoteTotal": 717323, "popularVotePercentage": "0.4611"}, "Roger MacBride": {"popularVoteTotal": 5042, "popularVotePercentage": "0.0032"}, "Gerald Ford": {"popularVoteTotal": 777732, "popularVotePercentage": "0.5000"}}, "topCandidate": "Gerald Ford", "electoralVotes": "9", "name": "Washington"}, {"candidateData": {"Eugene McCarthy": {"popularVoteTotal": 0, "popularVotePercentage": "0.0000"}, "Jimmy Carter": {"popularVoteTotal": 435914, "popularVotePercentage": "0.5807"}, "Roger MacBride": {"popularVoteTotal": 0, "popularVotePercentage": "0.0000"}, "Gerald Ford": {"popularVoteTotal": 314760, "popularVotePercentage": "0.4193"}}, "topCandidate": "Jimmy Carter", "electoralVotes": "6", "name": "West Virginia"}, {"candidateData": {"Eugene McCarthy": {"popularVoteTotal": 34943, "popularVotePercentage": "0.0166"}, "Jimmy Carter": {"popularVoteTotal": 1040232, "popularVotePercentage": "0.4950"}, "Roger MacBride": {"popularVoteTotal": 3814, "popularVotePercentage": "0.0018"}, "Gerald Ford": {"popularVoteTotal": 1004987, "popularVotePercentage": "0.4783"}}, "topCandidate": "Jimmy Carter", "electoralVotes": "11", "name": "Wisconsin"}, {"candidateData": {"Eugene McCarthy": {"popularVoteTotal": 624, "popularVotePercentage": "0.0040"}, "Jimmy Carter": {"popularVoteTotal": 62239, "popularVotePercentage": "0.3981"}, "Roger MacBride": {"popularVoteTotal": 89, "popularVotePercentage": "0.0006"}, "Gerald Ford": {"popularVoteTotal": 92717, "popularVotePercentage": "0.5930"}}, "topCandidate": "Gerald Ford", "electoralVotes": "3", "name": "Wyoming"}]}